runner_control_ao/__init__.py
runner_control_ao/version.py
runner_control_ao/infrastructure/__init__.py
runner_control_ao/infrastructure/ao.py
runner_control_ao/infrastructure/converter.py
runner_control_ao/infrastructure/do.py
runner_control_ao-0.1.0.dist-info/LICENSE
runner_control_ao-0.1.0.dist-info/METADATA
runner_control_ao-0.1.0.dist-info/WHEEL
runner_control_ao-0.1.0.dist-info/top_level.txt
runner_control_ao-0.1.0.dist-info/RECORD
