Metadata-Version: 2.1
Name: runner-control-ao
Version: 0.1.0
Summary: Exposed interface tool for runner service
Author: wangziling100
Author-email: wangziling100@163.com
Classifier: Programming Language :: Python :: 3
Classifier: License :: OSI Approved :: MIT License
License-File: LICENSE
